scabha/__init__.py
scabha/basetypes.py
scabha/cargo.py
scabha/configuratt.py
scabha/deprecated_substitutions.py
scabha/evaluator.py
scabha/exceptions.py
scabha/logging_utils.py
scabha/proc_utils.py
scabha/schema_utils.py
scabha/substitutions.py
scabha/types.py
scabha/validate.py
scabha-2.0.0.dist-info/LICENSE
scabha-2.0.0.dist-info/METADATA
scabha-2.0.0.dist-info/WHEEL
scabha-2.0.0.dist-info/top_level.txt
scabha-2.0.0.dist-info/RECORD
